{
  "physicalTable" : {
    "name" : "WC_ABSENCE_ALLOC_D",
    "sourceType" : "TABLE",
    "physicalColumns" : [ {
      "name" : "EMPLOYEE_ID",
      "dataType" : "NUMERIC",
      "length" : 0,
      "nullable" : true
    }, {
      "name" : "EMPLOYEE_NAME",
      "dataType" : "VARCHAR",
      "length" : 100,
      "nullable" : true
    }, {
      "name" : "LEAVE_DT",
      "dataType" : "VARCHAR",
      "length" : 20,
      "nullable" : true
    }, {
      "name" : "ABS_HOUR",
      "dataType" : "NUMERIC",
      "length" : 0,
      "nullable" : true
    } ],
    "caching" : {
      "enable" : true,
      "expiryTime" : 0
    }
  }
}